colabcode/__init__.py
colabcode/code.py
colabjupyter-0.1.0.data/scripts/colabcode
colabjupyter-0.1.0.dist-info/LICENSE
colabjupyter-0.1.0.dist-info/METADATA
colabjupyter-0.1.0.dist-info/WHEEL
colabjupyter-0.1.0.dist-info/top_level.txt
colabjupyter-0.1.0.dist-info/RECORD
