Metadata-Version: 2.1
Name: colabjupyter
Version: 0.1.0
Summary: ColabJupyter - Run Jupyter Lab On Colab
Home-page: https://github.com/nekologist/colabjupyter
Author: Nekologist
Author-email: ice@memeware.net
License: MIT License
Platform: linux
Platform: unix
Requires-Python: >3.5.2
Requires-Dist: pyngrok (>=4.1.12)
